Metadata-Version: 1.1
Name: xmi2odoo
Version: 1.4.0
Summary: XMI Conversor to Odoo modules.
Home-page: http://www.moldeointeractive.com.ar/
Author: Cristian S. Rocha
Author-email: cristian.rocha@moldeo.coop
License: UNKNOWN
Platform: UNKNOWN
Classifier: Development Status :: 5 - Production/Stable
Classifier: Environment :: Console
Classifier: Intended Audience :: Developers
Classifier: License :: OSI Approved :: GNU General Public License v3 or later (GPLv3+)
Classifier: Natural Language :: English
Classifier: Operating System :: Unix
Classifier: Programming Language :: Python :: 2.6
Classifier: Topic :: Software Development :: Build Tools
